sudio.libs/libgcc_s-1257a076.so.1
sudio.libs/libstdc++-0530927c.so.6.0.32
sudio/_suio.cpython-311-i386-linux-musl.so
sudio/_rateshift.cpython-311-i386-linux-musl.so
sudio/pipeline.py
sudio/__init__.py
sudio/core.py
sudio/io/_webio.py
sudio/io/__init__.py
sudio/rateshift/__init__.py
sudio/metadata/metadata.py
sudio/metadata/__init__.py
sudio/metadata/audio_record_database.py
sudio/types/pipelineonbusytype.py
sudio/types/__init__.py
sudio/types/pipelineprocesstype.py
sudio/types/error.py
sudio/types/name.py
sudio/types/enum.py
sudio/stream/streamingtimecontroller.py
sudio/stream/streamcontrol.py
sudio/stream/__init__.py
sudio/stream/stream.py
sudio/process/audio_wrap.py
sudio/process/__init__.py
sudio/process/fx/_fade_envelope.cpython-311-i386-linux-musl.so
sudio/process/fx/_tempo.pxd
sudio/process/fx/pitch_shifter.py
sudio/process/fx/_pitch_shifter.pxd
sudio/process/fx/_fade_envelope.pxd
sudio/process/fx/_channel_mixer.cpython-311-i386-linux-musl.so
sudio/process/fx/_pitch_shifter.cpython-311-i386-linux-musl.so
sudio/process/fx/fx.py
sudio/process/fx/_tempo.pyx
sudio/process/fx/__init__.py
sudio/process/fx/channel_mixer.py
sudio/process/fx/_tempo.cpython-311-i386-linux-musl.so
sudio/process/fx/_pitch_shifter.pyx
sudio/process/fx/fade_envelope.py
sudio/process/fx/tempo.py
sudio/process/fx/_fade_envelope.pyx
sudio/process/fx/gain.py
sudio/process/fx/_channel_mixer.pyx
sudio/audiosys/cacheman.py
sudio/audiosys/__init__.py
sudio/audiosys/sync.py
sudio/utils/typeconversion.py
sudio/utils/io.py
sudio/utils/channel.py
sudio/utils/strtool.py
sudio/utils/__init__.py
sudio/utils/math.cpython-311-i386-linux-musl.so
sudio/utils/timed_indexed_string.py
sudio/utils/math.pyx
sudio/utils/math.pxd
sudio/utils/window.py
sudio-1.0.10.dist-info/top_level.txt
sudio-1.0.10.dist-info/RECORD
sudio-1.0.10.dist-info/LICENSE
sudio-1.0.10.dist-info/METADATA
sudio-1.0.10.dist-info/WHEEL
