Metadata-Version: 2.1
Name: sudio
Version: 1.0.10
Summary: Audio Processing Platform
Author-email: Hossein Zahaki <mrzahaki@gmail.com>
License:              GNU AFFERO GENERAL PUBLIC LICENSE
Project-URL: source, https://github.com/mrzahaki/sudio
Classifier: Development Status :: 3 - Alpha
Classifier: Intended Audience :: Developers
Classifier: License :: OSI Approved :: GNU Affero General Public License v3
Classifier: Programming Language :: C
Classifier: Programming Language :: Python
Classifier: Programming Language :: Python :: 3
Classifier: Programming Language :: Python :: 3.10
Classifier: Programming Language :: Python :: 3.11
Classifier: Programming Language :: Python :: 3.12
Classifier: Programming Language :: Python :: 3 :: Only
Classifier: Typing :: Typed
Classifier: Operating System :: Microsoft :: Windows
Classifier: Operating System :: POSIX
Classifier: Operating System :: Unix
Classifier: Operating System :: MacOS
Requires-Python: >=3.10
License-File: LICENSE
Requires-Dist: scipy>=1.12.0
Requires-Dist: numpy>=2.0.1
